collabi/__init__.py
collabi/__main__.py
collabi/accelerator.py
collabi/all_help_action.py
collabi/auth.py
collabi/cli.py
collabi/cloud_config.py
collabi/collab.py
collabi/core.py
collabi/formatter.py
collabi/lazy_file.py
collabi/open_struct.py
collabi/rest.py
collabi-0.1.9.dist-info/METADATA
collabi-0.1.9.dist-info/RECORD
collabi-0.1.9.dist-info/WHEEL
collabi-0.1.9.dist-info/entry_points.txt
collabi-0.1.9.dist-info/top_level.txt
