Metadata-Version: 2.1
Name: collabi
Version: 0.1.9
Summary: UnityCloud Collaboration Command Line Interface
Home-page: https://github.com/UnityTech/unitycloud-collab-cli
Author: Unity Technologies, ApS
Author-email: collabsupport@unity3d.com
License: BSD-3-Clause
Platform: UNKNOWN
Classifier: Development Status :: 3 - Alpha
Classifier: Programming Language :: Python
Classifier: Programming Language :: Python :: 2
Classifier: Programming Language :: Python :: 2.7
Classifier: Environment :: Console
Classifier: Intended Audience :: Developers
Classifier: License :: OSI Approved :: BSD License
Classifier: Topic :: Software Development
Classifier: Topic :: Terminals
Classifier: Topic :: Utilities
Requires-Dist: python-dateutil (==2.7.3)
Requires-Dist: requests (==2.18.4)
Requires-Dist: grequests (==0.3.0)
Requires-Dist: humanize (==0.5.1)
Requires-Dist: tabulate (==0.8.2)
Requires-Dist: send2trash (==1.5.0)
Requires-Dist: tqdm (==4.23.4)
Requires-Dist: keyring (==12.2.1)
Requires-Dist: filelock (==3.0.4)
